mattstash/__init__.py
mattstash/core.py
mattstash/credential_store.py
mattstash/module_functions.py
mattstash/py.typed
mattstash/version_manager.py
mattstash/builders/__init__.py
mattstash/builders/db_url.py
mattstash/builders/s3_client.py
mattstash/cli/__init__.py
mattstash/cli/main.py
mattstash/cli/handlers/__init__.py
mattstash/cli/handlers/base.py
mattstash/cli/handlers/db_url.py
mattstash/cli/handlers/delete.py
mattstash/cli/handlers/get.py
mattstash/cli/handlers/list.py
mattstash/cli/handlers/put.py
mattstash/cli/handlers/s3_test.py
mattstash/cli/handlers/setup.py
mattstash/cli/handlers/versions.py
mattstash/core/__init__.py
mattstash/core/bootstrap.py
mattstash/core/entry_manager.py
mattstash/core/mattstash.py
mattstash/core/password_resolver.py
mattstash/models/__init__.py
mattstash/models/config.py
mattstash/models/credential.py
mattstash/utils/__init__.py
mattstash/utils/exceptions.py
mattstash-0.1.2.dist-info/METADATA
mattstash-0.1.2.dist-info/WHEEL
mattstash-0.1.2.dist-info/entry_points.txt
mattstash-0.1.2.dist-info/licenses/LICENSE
mattstash-0.1.2.dist-info/RECORD
