Metadata-Version: 2.4
Name: mattstash
Version: 0.1.2
Summary: Tiny KeePass-powered secrets accessor with optional S3 helper and Postgres URL builder.
Project-URL: Homepage, https://github.com/cornyhorse/mattstash
Project-URL: Repository, https://github.com/cornyhorse/mattstash
Project-URL: Issues, https://github.com/cornyhorse/mattstash/issues
Project-URL: Changelog, https://github.com/cornyhorse/mattstash/releases
Author: Matthew Kingsbury
License: MIT License
License-File: LICENSE
Keywords: cli,connection-string,credentials-store,keepass,password-manager,postgres,s3,secrets
Classifier: Development Status :: 3 - Alpha
Classifier: Environment :: Console
Classifier: Intended Audience :: Developers
Classifier: License :: OSI Approved :: MIT License
Classifier: Operating System :: OS Independent
Classifier: Programming Language :: Python :: 3
Classifier: Programming Language :: Python :: 3.9
Classifier: Programming Language :: Python :: 3.10
Classifier: Programming Language :: Python :: 3.11
Classifier: Programming Language :: Python :: 3.12
Classifier: Topic :: Security :: Cryptography
Classifier: Topic :: Software Development :: Libraries :: Python Modules
Classifier: Topic :: Utilities
Classifier: Typing :: Typed
Requires-Python: >=3.9
Requires-Dist: pykeepass<5.0,>=4.1
Provides-Extra: s3
Requires-Dist: boto3<2.0,>=1.28; extra == 's3'
Requires-Dist: botocore<2.0,>=1.31; extra == 's3'
